LICENSE
NOTICE
README.md
setup.py
aas/__init__.py
aas/py.typed
aas/adapter/__init__.py
aas/adapter/_generic.py
aas/adapter/aasx.py
aas/adapter/json/__init__.py
aas/adapter/json/aasJSONSchema.json
aas/adapter/json/json_deserialization.py
aas/adapter/json/json_serialization.py
aas/adapter/xml/AAS.xsd
aas/adapter/xml/AAS_ABAC.xsd
aas/adapter/xml/IEC61360.xsd
aas/adapter/xml/__init__.py
aas/adapter/xml/xml_deserialization.py
aas/adapter/xml/xml_serialization.py
aas/backend/__init__.py
aas/backend/backends.py
aas/backend/couchdb.py
aas/compliance_tool/__init__.py
aas/compliance_tool/cli.py
aas/compliance_tool/compliance_check_aasx.py
aas/compliance_tool/compliance_check_json.py
aas/compliance_tool/compliance_check_xml.py
aas/compliance_tool/state_manager.py
aas/examples/__init__.py
aas/examples/tutorial_aasx.py
aas/examples/tutorial_backend_couchdb.py
aas/examples/tutorial_create_simple_aas.py
aas/examples/tutorial_serialization_deserialization.py
aas/examples/tutorial_storage.py
aas/examples/data/TestFile.pdf
aas/examples/data/__init__.py
aas/examples/data/_helper.py
aas/examples/data/example_aas.py
aas/examples/data/example_aas_mandatory_attributes.py
aas/examples/data/example_aas_missing_attributes.py
aas/examples/data/example_concept_description.py
aas/examples/data/example_submodel_template.py
aas/model/__init__.py
aas/model/aas.py
aas/model/base.py
aas/model/concept.py
aas/model/datatypes.py
aas/model/provider.py
aas/model/security.py
aas/model/submodel.py
aas/util/__init__.py
aas/util/identification.py
aas/util/traversal.py
pyi40aas.egg-info/PKG-INFO
pyi40aas.egg-info/SOURCES.txt
pyi40aas.egg-info/dependency_links.txt
pyi40aas.egg-info/entry_points.txt
pyi40aas.egg-info/not-zip-safe
pyi40aas.egg-info/requires.txt
pyi40aas.egg-info/top_level.txt