Metadata-Version: 2.1
Name: pyi40aas
Version: 0.2.3
Summary: An implementation of the Asset Administration Shell for Industry 4.0 systems
Home-page: https://git.rwth-aachen.de/acplt/pyi40aas
Author: Chair of Process Control Engineering, RWTH Aachen
Author-email: m.thies@plt.rwth-aachen.de
License: UNKNOWN
Platform: UNKNOWN
Classifier: Programming Language :: Python :: 3
Classifier: License :: OSI Approved :: Eclipse Public License 2.0 (EPL-2.0)
Classifier: License :: OSI Approved :: Apache Software License
Classifier: Operating System :: OS Independent
Classifier: Development Status :: 3 - Alpha
Requires-Python: >=3.6
License-File: LICENSE
License-File: NOTICE
